{"3":{"password":"3","email":"3@gmail.com"},"34":{"password":"75","email":"lexy!@hawaii.edu"},"dport":{"name":"Dan Port","password":"portspassword","email":"dport@hawaii.edu"},"kazman":{"name":"Rick Kazman","password":"kazmanpassword","email":"kazman@hawaii.edu"},"itm352":{"password":"000000","email":"gmail@gmail.com"},"newuser":{"password":"newpass","email":"newuser@user.com","name":"The New Guy"},"Lexy":{"password":"23","email":"lexy@hawaii.edu"},"Lexy!":{"password":"5","email":"lexy!@hawaii.edu"},"dennisal":{"password":"000000","email":"gmail@gmail.com"}}